weatherclient/__init__.py
weatherclient/api.py
weatherclient_eldar-0.1.0.dist-info/licenses/LICENSE
weatherclient_eldar-0.1.0.dist-info/METADATA
weatherclient_eldar-0.1.0.dist-info/WHEEL
weatherclient_eldar-0.1.0.dist-info/top_level.txt
weatherclient_eldar-0.1.0.dist-info/RECORD
