Metadata-Version: 2.4
Name: weatherclient-eldar
Version: 0.1.0
Summary: Simple Python client for OpenWeatherMap API
Home-page: https://github.com/eldar/weatherclient
Author: Eldar Eliyev
Author-email: eldar@example.com
Classifier: Programming Language :: Python :: 3
Classifier: License :: OSI Approved :: MIT License
Classifier: Operating System :: OS Independent
Requires-Python: >=3.8
License-File: LICENSE
Requires-Dist: requests
Dynamic: author
Dynamic: author-email
Dynamic: classifier
Dynamic: description-content-type
Dynamic: home-page
Dynamic: license-file
Dynamic: requires-dist
Dynamic: requires-python
Dynamic: summary
